LICENSE
README.md
setup.py
chff/__init__.py
chff/links.py
chff.egg-info/PKG-INFO
chff.egg-info/SOURCES.txt
chff.egg-info/dependency_links.txt
chff.egg-info/not-zip-safe
chff.egg-info/requires.txt
chff.egg-info/top_level.txt