Metadata-Version: 1.1
Name: chff
Version: 0.1.4
Summary: Overlay Network Reference Implementation
Home-page: http://github.com/mnes-io/chff
Author: Charles Perkins
Author-email: charlesap@gmail.com
License: MIT
Platform: UNKNOWN
Classifier: Development Status :: 1 - Planning
Classifier: License :: OSI Approved :: MIT License
Classifier: Programming Language :: Python :: 3
Classifier: Topic :: Security :: Cryptography
